[
  { "id": 1, "name": "Rahul Sharma", "email": "rahul@gmail.com", "age": 21 },
  { "id": 2, "name": "Priya Singh", "email": "priya@gmail.com", "age": 22 },
  { "id": 3, "name": "Amit Verma", "email": "amit@gmail.com", "age": 23 },
  { "id": 4, "name": "Sneha Patel", "email": "sneha@gmail.com", "age": 20 },
  { "id": 5, "name": "Arjun Nair", "email": "arjun@gmail.com", "age": 24 },
  { "id": 6, "name": "Neha Gupta", "email": "neha@gmail.com", "age": 22 },
  { "id": 7, "name": "Rohan Mehta", "email": "rohan@gmail.com", "age": 21 },
  { "id": 8, "name": "Kavya Reddy", "email": "kavya@gmail.com", "age": 23 },
  { "id": 9, "name": "Vikram Joshi", "email": "vikram@gmail.com", "age": 25 },
  { "id": 10, "name": "Ananya Das", "email": "ananya@gmail.com", "age": 20 },
  { "id": 11, "name": "Manish Kumar", "email": "manish@gmail.com", "age": 24 },
  { "id": 12, "name": "Pooja Agarwal", "email": "pooja@gmail.com", "age": 22 },
  { "id": 13, "name": "Karan Malhotra", "email": "karan@gmail.com", "age": 23 },
  { "id": 14, "name": "Divya Iyer", "email": "divya@gmail.com", "age": 21 },
  { "id": 15, "name": "Siddharth Jain", "email": "sid@gmail.com", "age": 26 },
  { "id": 16, "name": "Ritika Kapoor", "email": "ritika@gmail.com", "age": 22 },
  { "id": 17, "name": "Aditya Kulkarni", "email": "aditya@gmail.com", "age": 24 },
  { "id": 18, "name": "Meera Nair", "email": "meera@gmail.com", "age": 23 },
  { "id": 19, "name": "Yash Shah", "email": "yash@gmail.com", "age": 21 },
  { "id": 20, "name": "Ishita Chatterjee", "email": "ishita@gmail.com", "age": 22 },
  { "id": 21, "name": "Harsh Patel", "email": "harsh@gmail.com", "age": 23 },
  { "id": 22, "name": "Nisha Reddy", "email": "nisha@gmail.com", "age": 20 },
  { "id": 23, "name": "Varun Bansal", "email": "varun@gmail.com", "age": 24 },
  { "id": 24, "name": "Tanvi Desai", "email": "tanvi@gmail.com", "age": 22 },
  { "id": 25, "name": "Rajat Saxena", "email": "rajat@gmail.com", "age": 25 },
  { "id": 26, "name": "Shreya Ghosh", "email": "shreya@gmail.com", "age": 21 },
  { "id": 27, "name": "Abhishek Tiwari", "email": "abhishek@gmail.com", "age": 23 },
  { "id": 28, "name": "Aisha Khan", "email": "aisha@gmail.com", "age": 22 },
  { "id": 29, "name": "Nikhil Arora", "email": "nikhil@gmail.com", "age": 24 },
  { "id": 30, "name": "Simran Kaur", "email": "simran@gmail.com", "age": 20 },
  { "id": 31, "name": "Deepak Yadav", "email": "deepak@gmail.com", "age": 26 },
  { "id": 32, "name": "Komal Sharma", "email": "komal@gmail.com", "age": 23 },
  { "id": 33, "name": "Rakesh Mishra", "email": "rakesh@gmail.com", "age": 25 },
  { "id": 34, "name": "Pallavi Sen", "email": "pallavi@gmail.com", "age": 22 },
  { "id": 35, "name": "Mohit Gupta", "email": "mohit@gmail.com", "age": 24 },
  { "id": 36, "name": "Neeraj Singh", "email": "neeraj@gmail.com", "age": 21 },
  { "id": 37, "name": "Aarav Kapoor", "email": "aarav@gmail.com", "age": 23 },
  { "id": 38, "name": "Diya Shah", "email": "diya@gmail.com", "age": 22 },
  { "id": 39, "name": "Kabir Mehta", "email": "kabir@gmail.com", "age": 24 },
  { "id": 40, "name": "Isha Verma", "email": "isha@gmail.com", "age": 21 },
  { "id": 41, "name": "Lakshya Jain", "email": "lakshya@gmail.com", "age": 23 },
  { "id": 42, "name": "Riya Sinha", "email": "riya@gmail.com", "age": 20 },
  { "id": 43, "name": "Gaurav Arora", "email": "gaurav@gmail.com", "age": 25 },
  { "id": 44, "name": "Ankit Sharma", "email": "ankit@gmail.com", "age": 24 },
  { "id": 45, "name": "Sanya Malhotra", "email": "sanya@gmail.com", "age": 22 },
  { "id": 46, "name": "Dev Patel", "email": "dev@gmail.com", "age": 23 },
  { "id": 47, "name": "Kriti Nair", "email": "kriti@gmail.com", "age": 21 },
  { "id": 48, "name": "Rohit Agarwal", "email": "rohit@gmail.com", "age": 26 },
  { "id": 49, "name": "Tanya Bhatia", "email": "tanya@gmail.com", "age": 22 },
  { "id": 50, "name": "Aryan Kapoor", "email": "aryan@gmail.com", "age": 23 }
]